gitfig/__init__.py
gitfig/blobconfig.py
gitfig-0.1.4.dist-info/METADATA
gitfig-0.1.4.dist-info/WHEEL
gitfig-0.1.4.dist-info/top_level.txt
gitfig-0.1.4.dist-info/RECORD
