Metadata-Version: 2.1
Name: gitfig
Version: 0.1.4
Summary: UNKNOWN
Home-page: UNKNOWN
Author: André Carneiro
Author-email: acarneiro.dev@gmail.com
License: UNKNOWN
Platform: UNKNOWN
Classifier: Development Status :: 3 - Alpha
Classifier: Intended Audience :: Information Technology
Classifier: Natural Language :: English
Classifier: Operating System :: OS Independent
Classifier: Programming Language :: Python :: 3 :: Only
Requires-Dist: gitpython
Requires-Dist: PyYaml
